[
  {
    "referenceType": "Journal Article",
    "title": "How to write an abstract that will be accepted for presentation at a national meeting",
    "author": "Pierson, David J.",
    "url": "http:\/\/rc.rcjournal.com\/content\/49\/10\/1206",
    "year": "2004",
    "startPage": "1206-1212",
    "isbn": "0020-1324",
    "volume": "49",
    "itemLink": "http:\/\/lr.library.uq.edu.au\/items\/04B2C05B-E0E3-BA3D-814B-A4E939AFC0A6.html"
  },
  {
    "referenceType": "Journal Article",
    "title": "Scope, Completeness, and Accuracy of Drug Information in Wikipedia",
    "author": "Clauson, K. A.; Polen, H. H.; Boulos, M. N. K.",
    "year": "2008",
    "endPage": "1821",
    "startPage": "1814",
    "isbn": "1060-0280; 1542-6270",
    "volume": "42",
    "itemLink": "http:\/\/lr.library.uq.edu.au\/items\/04E742EF-3557-A282-5042-882EB50E0A82.html"
  },
  {
    "referenceType": "Book",
    "title": "Pocket guide: pharmacokinetics made easy",
    "importance": "Recommended",
    "author": "Birkett, D. J.",
    "publisher": "McGraw-Hill Australia",
    "year": "2010",
    "placePublished": "North Ryde, N.S.W.",
    "isbn": "9780070285279",
    "catalogueRecordId": "b2450898",
    "itemLink": "http:\/\/lr.library.uq.edu.au\/items\/0733D364-9C1A-568B-31F1-A760470B4EAD.html"
  },
  {
    "referenceType": "Journal Article",
    "title": "Australian adults use complementary and alternative medicine in the treatment of chronic illness: a national study",
    "author": "Armstrong, Andrew R.; Thi\u00e9baut, Sophie P.; Brown, Laurie J.",
    "year": "2011",
    "endPage": "390",
    "startPage": "384",
    "isbn": "1753-6405",
    "volume": "35",
    "itemLink": "http:\/\/lr.library.uq.edu.au\/items\/090F6637-6F4D-C531-2A5A-C3465B78B905.html"
  },
  {
    "referenceType": "Journal Article",
    "title": "Pharmacogenetics and human genetic polymorphisms",
    "author": "Daly, Ann K.",
    "year": "2010",
    "startPage": "435\u2013449",
    "isbn": "0264-6021; 1470-8728",
    "volume": "429",
    "itemLink": "http:\/\/lr.library.uq.edu.au\/items\/0B99DA6F-40E1-DBA6-7D72-A0F4145CAC57.html"
  },
  {
    "referenceType": "Journal Article",
    "title": "Motivational Interviewing",
    "author": "Levensky, Eric Ross; Forcehimes, Alyssa; O\u02bcDonohue, William T.",
    "year": "2007",
    "endPage": "58",
    "startPage": "50",
    "isbn": "0002-936X",
    "volume": "107",
    "itemLink": "http:\/\/lr.library.uq.edu.au\/items\/129CC75F-B53B-4CC1-C103-71A09F2B41F5.html"
  },
  {
    "referenceType": "Journal Article",
    "title": "How to use a noninferiority trial",
    "author": "Mulla, Sohail M.; Scott, Ian A.; Jackevicius, Cynthia A.",
    "year": "2012",
    "startPage": "2605",
    "isbn": "0098-7484",
    "volume": "308",
    "itemLink": "http:\/\/lr.library.uq.edu.au\/items\/156BE87A-78AD-0866-F29F-161AC34FD50A.html"
  },
  {
    "referenceType": "Webpage",
    "title": "Past Central Exam Papers",
    "notes": "Follow the link and search for past exam papers by course code.",
    "url": "https:\/\/www.library.uq.edu.au\/#exampapers",
    "itemLink": "http:\/\/lr.library.uq.edu.au\/items\/17709AA4-5422-F98A-1891-3CD594A7D637.html"
  },
  {
    "referenceType": "Journal Article",
    "title": "Preventing overdiagnosis: how to stop harming the healthy",
    "author": "Moynihan, R.; Doust, J.; Henry, D.",
    "year": "2012",
    "endPage": "e3502",
    "startPage": "e3502",
    "isbn": "1756-1833",
    "volume": "344",
    "itemLink": "http:\/\/lr.library.uq.edu.au\/items\/181F400A-0A93-F947-DEA7-E23CECC844CB.html"
  },
  {
    "referenceType": "Journal Article",
    "title": "Prasugrel versus Clopidogrel in Patients with Acute Coronary Syndromes",
    "author": "Wiviott, Stephen D.; Braunwald, Eugene; McCabe, Carolyn H.",
    "year": "2007",
    "endPage": "2015",
    "startPage": "2001",
    "isbn": "0028-4793; 1533-4406",
    "volume": "357",
    "itemLink": "http:\/\/lr.library.uq.edu.au\/items\/18B5E68B-7B30-A242-7A3B-934982C87A01.html"
  },
  {
    "referenceType": "Webpage",
    "title": "eTG complete (Therapeutic Guidelines)",
    "importance": "Required",
    "url": "http:\/\/online.tg.org.au.ezproxy.library.uq.edu.au\/ip\/desktop\/index.htm",
    "itemLink": "http:\/\/lr.library.uq.edu.au\/items\/2242DB14-FE87-C348-52A2-C4FA87BBCCBF.html"
  },
  {
    "referenceType": "Journal Article",
    "title": "Diagnosis in General Practice: using probabilistic reasoning",
    "author": "Doust, J.",
    "year": "2009",
    "endPage": "b3823",
    "startPage": "b3823",
    "isbn": "0959-8138; 1468-5833",
    "volume": "339",
    "itemLink": "http:\/\/lr.library.uq.edu.au\/items\/29B302BB-5C45-795D-A58E-BABC85263524.html"
  },
  {
    "referenceType": "Journal Article",
    "title": "Responding to drug information requests",
    "author": "Nathan, J. P.; Gim, S.",
    "year": "2009",
    "endPage": "711",
    "startPage": "706",
    "isbn": "1079-2082",
    "volume": "66",
    "itemLink": "http:\/\/lr.library.uq.edu.au\/items\/2C8F3BF8-14C4-50E0-0570-AD1B442CE691.html"
  },
  {
    "referenceType": "Journal Article",
    "title": "How to read a paper: Assessing the methodological quality of published papers",
    "author": "Greenhalgh, Trisha",
    "year": "1997",
    "endPage": "308",
    "startPage": "305",
    "isbn": "0959-8138; 1468-5833",
    "volume": "315",
    "itemLink": "http:\/\/lr.library.uq.edu.au\/items\/2E38F522-B530-9B48-B8A2-4D5CB5E613AA.html"
  },
  {
    "referenceType": "Journal Article",
    "title": "How to read a paper : getting your bearings (deciding what the paper is about)",
    "author": "Greenhalgh, Trisha",
    "year": "1997",
    "endPage": "246",
    "startPage": "243",
    "isbn": "0959-8138; 1468-5833",
    "volume": "315",
    "itemLink": "http:\/\/lr.library.uq.edu.au\/items\/30CEB89F-CCC2-7D37-B778-E9CD6AD135CE.html"
  },
  {
    "referenceType": "Book",
    "title": "Users' guides to the medical literature: a manual for evidence-based clinical practice",
    "importance": "Recommended",
    "author": "Guyatt, Gordon; Rennie, Drummond; Meade, Maureen; Cook, Deborah; American Medical Association",
    "publisher": "McGraw-Hill Education",
    "year": "2015",
    "placePublished": "New York",
    "isbn": "0071790713; 0071816399; 9780071790710; 9780071816397",
    "catalogueRecordId": "b3569579",
    "volume": "JAMAevidence",
    "itemLink": "http:\/\/lr.library.uq.edu.au\/items\/3281EC9D-0445-00D6-5559-608DE6E1FA1F.html"
  },
  {
    "referenceType": "Journal Article",
    "title": "Users' Guides to the Medical Literature: XXV: Evidence-based medicine: Principles for Applying the Users' Guides to Patient Care",
    "author": "Guyatt, Gordon H.; Haynes, R. Brian; Jaeschke, Roman Z.; for the Evidence-Based Medicine Working Group",
    "year": "2000",
    "startPage": "1290-1296",
    "isbn": "0098-7484",
    "volume": "284",
    "itemLink": "http:\/\/lr.library.uq.edu.au\/items\/390D8895-F34E-852E-54CB-35826F336D92.html"
  },
  {
    "referenceType": "Journal Article",
    "title": "Usefulness of herbal and dietary supplement references",
    "author": "Sweet, Burgunda V.; Gay, Wendy E.; Leady, Michelle A.",
    "year": "2003",
    "endPage": "499",
    "startPage": "494",
    "isbn": "10600280; 15426270",
    "volume": "37",
    "itemLink": "http:\/\/lr.library.uq.edu.au\/items\/40948EEE-4760-6624-7F73-213FB0AEDA84.html"
  },
  {
    "referenceType": "Journal Article",
    "title": "The idolatry of the surrogate",
    "author": "Yudkin, J. S.; Lipska, K. J.; Montori, V. M.",
    "year": "2011",
    "endPage": "d7995",
    "startPage": "d7995",
    "isbn": "0959-8138; 1468-5833",
    "volume": "343",
    "itemLink": "http:\/\/lr.library.uq.edu.au\/items\/44D7A352-3F58-8024-41A1-CEF1D15C05D8.html"
  },
  {
    "referenceType": "Journal Article",
    "title": "Mechanisms underlying food\u2013drug interactions: Inhibition of intestinal metabolism and transport",
    "author": "Won, Christina S.; Oberlies, Nicholas H.; Paine, Mary F.",
    "year": "2012",
    "endPage": "201",
    "startPage": "186",
    "isbn": "01637258",
    "volume": "136",
    "itemLink": "http:\/\/lr.library.uq.edu.au\/items\/4842F59C-BF93-E340-57C1-11A98169FEDB.html"
  },
  {
    "referenceType": "Journal Article",
    "title": "Homeopathy: what does the best evidence tell us",
    "author": "Ernst, Edzard",
    "publisher": "Sydney : Australasian Medical Publishing Co",
    "url": "https:\/\/www-mja-com-au.ezproxy.library.uq.edu.au\/journal\/2010\/192\/8\/homeopathy-what-does-best-evidence-tell-us",
    "year": "2010",
    "startPage": "458-460",
    "isbn": "0025-729X; 1326-5377",
    "volume": "192",
    "itemLink": "http:\/\/lr.library.uq.edu.au\/items\/4944C488-1273-15E9-7F58-E80C4AAC5676.html"
  },
  {
    "referenceType": "Journal Article",
    "title": "Helping Patients Make and Sustain Healthy Changes: A Brief Introduction to Motivational Interviewing in Clinical Diabetes Care",
    "author": "Heisler, Michele",
    "publisher": "American Diabetes Association",
    "url": "http:\/\/search.proquest.com.ezproxy.library.uq.edu.au\/docview\/199412488\/abstract\/1431D3E4BE03722EFC6\/1?accountid=14723",
    "year": "2008",
    "endPage": "165",
    "startPage": "161",
    "isbn": "08918929",
    "volume": "26",
    "itemLink": "http:\/\/lr.library.uq.edu.au\/items\/4E41C977-7E6F-EBA4-020A-A7C84356148F.html"
  },
  {
    "referenceType": "Journal Article",
    "title": "Practical teaching: great presentations every time",
    "author": "Irby, David M.",
    "year": "2004",
    "endPage": "9",
    "startPage": "5",
    "isbn": "1743-4971; 1743-498X",
    "volume": "1",
    "itemLink": "http:\/\/lr.library.uq.edu.au\/items\/4FAE29D2-57AC-AF30-37E9-58E8577256C4.html"
  },
  {
    "referenceType": "Journal Article",
    "title": "Users' Guides to the Medical Literature: XIX: Applying clinical trial results. A: How to use an article measuring the effect of an intervention on surrogate end points",
    "author": "Bucher, Heiner C.; Guyatt, Gordon H.; Cook, Deborah J.; for the Evidence-Based Medicine Working Group",
    "year": "1999",
    "startPage": "771",
    "isbn": "0098-7484",
    "volume": "282",
    "itemLink": "http:\/\/lr.library.uq.edu.au\/items\/528587C9-882E-AE0C-D57F-C42DA28DF36E.html"
  },
  {
    "referenceType": "Journal Article",
    "title": "What the public learns about screening and diagnostic tests through the media",
    "author": "Jane Robertson, Amanda J. Wilson; Benjamin D. Ewald",
    "year": "2012",
    "startPage": "324-326",
    "isbn": "0025-729X; 1326-5377",
    "volume": "197",
    "itemLink": "http:\/\/lr.library.uq.edu.au\/items\/568E768F-49A3-4806-174B-F8BA97CE3565.html"
  },
  {
    "referenceType": "Journal Article",
    "title": "How to critically appraise an article",
    "author": "Young, Jane M.; Solomon, Michael J.",
    "year": "2009",
    "endPage": "91",
    "startPage": "82",
    "isbn": "1743-4378; 1743-4386",
    "volume": "6",
    "itemLink": "http:\/\/lr.library.uq.edu.au\/items\/6007FBF5-505B-AD15-F0C0-703BE3631379.html"
  },
  {
    "referenceType": "Journal Article",
    "title": "Users' Guides to the Medical Literature: XXII: how to use articles about clinical decision rules",
    "author": "McGinn, Thomas G.; Guyatt, Gordon H.; Wyer, Peter C.; for the Evidence-Based Medicine Working Group",
    "year": "2000",
    "startPage": "79-84",
    "isbn": "0098-7484",
    "volume": "284",
    "itemLink": "http:\/\/lr.library.uq.edu.au\/items\/66168EF2-E42A-ACEE-8078-B1F59D1E30B5.html"
  },
  {
    "referenceType": "Journal Article",
    "title": "Pharmacogenomics - drug disposition, drug targets, and side effects",
    "author": "Wood, Alastair J.J.; Evans, William E.; McLeod, Howard L.",
    "publisher": "Massachusetts Medical Society",
    "url": "http:\/\/search.proquest.com.ezproxy.library.uq.edu.au\/docview\/220163085?accountid=14723",
    "year": "2003",
    "endPage": "49",
    "startPage": "538",
    "isbn": "00284793",
    "volume": "348",
    "itemLink": "http:\/\/lr.library.uq.edu.au\/items\/68FB91A5-2B55-B78E-D4E9-9517F3DBECA2.html"
  },
  {
    "referenceType": "Journal Article",
    "title": "Users' Guides to the Medical Literature: XIV: How to decide on the applicability of clinical trial results to your patient",
    "author": "Dans, Antonio L.; Dans, Leonila F.; Guyatt, Gordon H.; for the Evidence-Based Medicine Working Group",
    "year": "1998",
    "startPage": "545",
    "isbn": "0098-7484",
    "volume": "279",
    "itemLink": "http:\/\/lr.library.uq.edu.au\/items\/7CDCD875-7210-E743-590D-3BBDA4EB7093.html"
  },
  {
    "referenceType": "Book",
    "title": "Clinical pharmacy: a practical approach",
    "importance": "Recommended",
    "author": "Hughes, Jeff; Donnelly, Richard; James-Chatgilaou, Greta; Society of Hospital Pharmacists of Australia",
    "publisher": "Macmillan Education Australia",
    "year": "2001",
    "placePublished": "South Yarra, Vic",
    "isbn": "0732980291",
    "catalogueRecordId": "b2060807",
    "itemLink": "http:\/\/lr.library.uq.edu.au\/items\/891DB561-EE72-36E6-B0B1-3D0E4D2F171B.html"
  },
  {
    "referenceType": "JFULL",
    "title": "Australian medicines handbook",
    "importance": "Required",
    "author": "Health Communication Network",
    "publisher": "Australian Medicines Handbook",
    "url": "http:\/\/ezproxy.library.uq.edu.au\/login?url=http:\/\/amh.net.au\/online",
    "placePublished": "Adelaide, S. Aust",
    "catalogueRecordId": "b1923410",
    "itemLink": "http:\/\/lr.library.uq.edu.au\/items\/8DF3D46E-9A84-46FC-6217-42065CD5AC1B.html"
  },
  {
    "referenceType": "Journal Article",
    "title": "How to write an abstract",
    "author": "Vrijhoef, H.J.M.; Steuten, L.M.G.",
    "year": "2007",
    "endPage": "127",
    "startPage": "124",
    "isbn": "15517853; 15517861",
    "volume": "4",
    "itemLink": "http:\/\/lr.library.uq.edu.au\/items\/9736DEB7-BC34-42E5-3726-004DB3276A72.html"
  },
  {
    "referenceType": "Journal Article",
    "title": "Fruit Juices as Perpetrators of Drug Interactions: The Role of Organic Anion\u2013Transporting Polypeptides",
    "author": "Dolton, M J; Roufogalis, B D; McLachlan, A J",
    "url": "http:\/\/onlinelibrary.wiley.com.ezproxy.library.uq.edu.au\/doi\/10.1038\/clpt.2012.159\/abstract",
    "year": "2012",
    "endPage": "630",
    "startPage": "622",
    "isbn": "0009-9236; 1532-6535",
    "volume": "92",
    "itemLink": "http:\/\/lr.library.uq.edu.au\/items\/9E8A8063-F4BE-4E5A-888B-9ED1FFD4CBB8.html"
  },
  {
    "referenceType": "Journal Article",
    "title": "Pharmacogenetics, drug-metabolizing enzymes, and clinical practice",
    "author": "Begg, Evan J., Gardiner, Sharon J.",
    "year": "2006",
    "startPage": "521-590",
    "isbn": "0031-6997; 1521-0081",
    "volume": "58",
    "itemLink": "http:\/\/lr.library.uq.edu.au\/items\/9EA48A7C-48E3-88CE-AC0D-DFE73E2593B3.html"
  },
  {
    "referenceType": "Journal Article",
    "title": "USERS guides to the medical literature: XVI: How to use a treatment recommendation",
    "author": "Guyatt, Gordon H.",
    "year": "1999",
    "startPage": "1836-1843",
    "isbn": "0098-7484",
    "volume": "281",
    "itemLink": "http:\/\/lr.library.uq.edu.au\/items\/A718CE9A-016E-8352-39BC-B850C44413C8.html"
  },
  {
    "referenceType": "Book",
    "title": "Instant clinical pharmacology",
    "importance": "Recommended",
    "author": "Begg, Evan J.",
    "publisher": "Blackwell Pub",
    "year": "2008",
    "placePublished": "Malden, Mass",
    "isbn": "1405150467; 9781405150460",
    "catalogueRecordId": "b2334792",
    "itemLink": "http:\/\/lr.library.uq.edu.au\/items\/AECC5161-F4BD-8687-7068-A1B8F891A8D2.html"
  },
  {
    "referenceType": "Journal Article",
    "title": "Special Considerations in Interpreting Liver Function Tests",
    "author": "Johnston, David E.",
    "year": "1999",
    "endPage": "2230",
    "startPage": "2223",
    "isbn": "0002-838X",
    "volume": "59",
    "itemLink": "http:\/\/lr.library.uq.edu.au\/items\/AFDEBCA1-5E6D-F09C-358F-63C24F30CDB0.html"
  },
  {
    "referenceType": "Journal Article",
    "title": "Evidence based medicine: what it is and what it isn't",
    "author": "Sackett, D. L.; Rosenberg, W. M. C.; Gray, J. A. M.",
    "year": "1996",
    "endPage": "72",
    "startPage": "71",
    "isbn": "0959-8146",
    "volume": "312",
    "itemLink": "http:\/\/lr.library.uq.edu.au\/items\/B7E6B2E6-1455-7EDF-DBD2-62D9CEA2136F.html"
  },
  {
    "referenceType": "Journal Article",
    "title": "Users guides to the medical literature: XX: Integrating research evidence with the care of the individual patient",
    "author": "McAlister, Finlay A.; Straus, Sharon E.; Guyatt, Gordon H.; for the Evidence-Based Medicine Working Group",
    "year": "2000",
    "startPage": "2829-2836",
    "isbn": "0098-7484",
    "volume": "283",
    "itemLink": "http:\/\/lr.library.uq.edu.au\/items\/C98B9CFE-92CE-35DF-B5B9-960BFF5FD865.html"
  },
  {
    "referenceType": "Book",
    "title": "Motivational interviewing in health care: helping patients change behavior",
    "importance": "Recommended",
    "author": "Rollnick, Stephen; Miller, William R.; Butler, Christopher",
    "publisher": "Guilford Press",
    "url": "http:\/\/www.UQL.eblib.com.au\/patron\/FullRecord.aspx?p=406031",
    "year": "2008",
    "placePublished": "New York",
    "isbn": "9781593858575",
    "catalogueRecordId": "b3034465",
    "volume": "Applications of motivational interviewing",
    "itemLink": "http:\/\/lr.library.uq.edu.au\/items\/CAD47EFD-E750-F8F8-EAE7-7737C3EF853A.html"
  },
  {
    "referenceType": "Book",
    "title": "Avery's drug treatment: a guide to the properties, choice, therapeutic use and economic value of drugs in disease management",
    "importance": "Recommended",
    "author": "Avery, Graeme S.; Speight, Trevor M.; Holford, Nicholas H.G.",
    "publisher": "Adis International",
    "year": "1997",
    "placePublished": "Auckland, N.Z.",
    "isbn": "0864710364",
    "catalogueRecordId": "b1876688",
    "itemLink": "http:\/\/lr.library.uq.edu.au\/items\/D34D7AC4-75ED-EDA8-F355-75F3DD1E4796.html"
  },
  {
    "referenceType": "Journal Article",
    "title": "Challenges to Evidence-Based Prescribing in Clinical Practice",
    "author": "Mamdani, M.; Ching, A.; Golden, B.",
    "year": "2008",
    "endPage": "707",
    "startPage": "704",
    "isbn": "1060-0280; 1542-6270",
    "volume": "42",
    "itemLink": "http:\/\/lr.library.uq.edu.au\/items\/DAC85CBA-4B04-293D-C345-5D8ABA5FB4CA.html"
  },
  {
    "referenceType": "Journal Article",
    "title": "Prescribing in renal disease",
    "author": "Faull, Randall",
    "url": "http:\/\/www.australianprescriber.com\/magazine\/30\/1\/17\/20",
    "year": "2007",
    "startPage": "17-20",
    "isbn": "0312-8008",
    "volume": "30",
    "itemLink": "http:\/\/lr.library.uq.edu.au\/items\/DF60DC57-FBBF-0776-D330-9A0620137EC8.html"
  },
  {
    "referenceType": "Journal Article",
    "title": "Problem-oriented drug information: physicians\u2019 expectations and impact on clinical practice",
    "author": "Hedegaard, U.; Damkier, P.",
    "year": "2009",
    "endPage": "522",
    "startPage": "515",
    "isbn": "0031-6970; 1432-1041",
    "volume": "65",
    "itemLink": "http:\/\/lr.library.uq.edu.au\/items\/E0424546-3238-4708-72C0-C3909A468136.html"
  },
  {
    "referenceType": "Journal Article",
    "title": "Genomics and Drug Response",
    "author": "Feero, W. Gregory; Guttmacher, Alan E.; Wang, Liewei",
    "year": "2011",
    "endPage": "1153",
    "startPage": "1144",
    "isbn": "0028-4793; 1533-4406",
    "volume": "364",
    "itemLink": "http:\/\/lr.library.uq.edu.au\/items\/E7131D31-DE27-1269-573C-FE02D44B574B.html"
  },
  {
    "referenceType": "Book",
    "title": "Abnormal laboratory results",
    "importance": "Recommended",
    "author": "Kellerman, Geoffrey",
    "publisher": "McGraw-Hill",
    "year": "2011",
    "placePublished": "North Ryde, N.S.W.",
    "isbn": "9780070998421",
    "catalogueRecordId": "b2744792",
    "itemLink": "http:\/\/lr.library.uq.edu.au\/items\/E90BB847-73A1-E9C8-DBCF-E78B6546E7BF.html"
  },
  {
    "referenceType": "Journal Article",
    "title": "Genotyping for drug-metabolizing enzymes: does the promise meet the reality?",
    "author": "Begg, Evan J., Gardiner, Sharon J.",
    "url": "http:\/\/www.futuremedicine.com.ezproxy.library.uq.edu.au\/doi\/abs\/10.1517\/14622416.5.8.1033",
    "year": "2004",
    "startPage": "1033-1036",
    "isbn": "1462-2416",
    "volume": "5",
    "itemLink": "http:\/\/lr.library.uq.edu.au\/items\/FF910340-1B01-10A9-5221-1D656C53A45E.html"
  }
]